osscmd/__init__.py
osscmd/__main__.py
osscmd/args.py
osscmd/conf.py
osscmd/log_util.py
osscmd/oss_ops.py
osscmd/package_info.py
osscmd/path_util.py
osscmd-0.0.1.dist-info/METADATA
osscmd-0.0.1.dist-info/WHEEL
osscmd-0.0.1.dist-info/entry_points.txt
osscmd-0.0.1.dist-info/top_level.txt
osscmd-0.0.1.dist-info/RECORD
