Metadata-Version: 2.1
Name: osscmd
Version: 0.0.1
Summary: oss related command line tools based on oss2
Home-page: UNKNOWN
License: UNKNOWN
Platform: UNKNOWN
Requires-Python: >3.6
Requires-Dist: oss2
Requires-Dist: loguru
